LyricMaster/__init__.py
LyricMaster/error.py
LyricMaster/lyric.py
LyricMasterAPI_LyricScrapping-1.0.0.dist-info/LICENSE
LyricMasterAPI_LyricScrapping-1.0.0.dist-info/METADATA
LyricMasterAPI_LyricScrapping-1.0.0.dist-info/WHEEL
LyricMasterAPI_LyricScrapping-1.0.0.dist-info/top_level.txt
LyricMasterAPI_LyricScrapping-1.0.0.dist-info/RECORD
